google_tunix-0.1.3.dist-info/licenses/LICENSE
tunix/__init__.py
tunix/cli/config.py
tunix/cli/grpo_main.py
tunix/cli/peft_main.py
tunix/cli/reward_fn/gsm8k.py
tunix/cli/reward_fn/gsm8k_verl.py
tunix/cli/utils/model.py
tunix/distillation/__init__.py
tunix/distillation/distillation_trainer.py
tunix/distillation/feature_extraction/__init__.py
tunix/distillation/feature_extraction/pooling.py
tunix/distillation/feature_extraction/projection.py
tunix/distillation/feature_extraction/sowed_module.py
tunix/distillation/strategies/__init__.py
tunix/distillation/strategies/attention.py
tunix/distillation/strategies/base_strategy.py
tunix/distillation/strategies/feature_pooling.py
tunix/distillation/strategies/feature_projection.py
tunix/distillation/strategies/logit.py
tunix/examples/data/math_dataset.py
tunix/examples/data/translation_dataset.py
tunix/generate/base_sampler.py
tunix/generate/beam_search.py
tunix/generate/mappings.py
tunix/generate/sampler.py
tunix/generate/tokenizer_adapter.py
tunix/generate/utils.py
tunix/generate/vllm_sampler.py
tunix/models/safetensors_loader.py
tunix/models/gemma/model.py
tunix/models/gemma/params.py
tunix/models/gemma/params_safetensors.py
tunix/models/gemma/sampler.py
tunix/models/gemma3/model.py
tunix/models/gemma3/params.py
tunix/models/gemma3/params_safetensors.py
tunix/models/llama3/__init__.py
tunix/models/llama3/mapping_vllm_jax.py
tunix/models/llama3/model.py
tunix/models/llama3/params.py
tunix/models/qwen2/__init__.py
tunix/models/qwen2/mapping_vllm_jax.py
tunix/models/qwen2/model.py
tunix/models/qwen2/params.py
tunix/models/qwen3/model.py
tunix/models/qwen3/params.py
tunix/oss/utils.py
tunix/rl/common.py
tunix/rl/reshard.py
tunix/rl/rl_cluster.py
tunix/rl/rl_learner.py
tunix/rl/trainer.py
tunix/rl/utils.py
tunix/rl/experimental/agentic/utils.py
tunix/rl/experimental/agentic/agents/agent_types.py
tunix/rl/experimental/agentic/agents/base_agent.py
tunix/rl/experimental/agentic/agents/tool_agent.py
tunix/rl/experimental/agentic/environments/base_environment.py
google_tunix-0.1.3.dist-info/METADATA
google_tunix-0.1.3.dist-info/WHEEL
google_tunix-0.1.3.dist-info/top_level.txt
google_tunix-0.1.3.dist-info/RECORD
