Metadata-Version: 2.4
Name: google-tunix
Version: 0.1.3
Summary: A lightweight JAX-native LLM post-training framework.
Author-email: Tunix Developers <tunix-dev@google.com>
License-Expression: Apache-2.0
Project-URL: Source, https://github.com/google/tunix
Classifier: Development Status :: 3 - Alpha
Classifier: Intended Audience :: Developers
Classifier: Intended Audience :: Science/Research
Classifier: Programming Language :: Python :: 3.11
Classifier: Programming Language :: Python :: 3.12
Classifier: Programming Language :: Python :: 3.13
Classifier: Topic :: Scientific/Engineering :: Artificial Intelligence
Requires-Python: >=3.11
License-File: LICENSE
Requires-Dist: datasets
Requires-Dist: flax>=0.11.1
Requires-Dist: gcsfs
Requires-Dist: grain
Requires-Dist: huggingface_hub
Requires-Dist: jaxtyping
Requires-Dist: jinja2
Requires-Dist: kagglehub
Requires-Dist: numba
Requires-Dist: omegaconf
Requires-Dist: python-dotenv
Requires-Dist: qwix
Requires-Dist: sentencepiece
Requires-Dist: tensorboardX
Requires-Dist: tensorflow_datasets
Requires-Dist: tqdm
Requires-Dist: transformers
Requires-Dist: hf_transfer
Provides-Extra: docs
Requires-Dist: sphinx>=8.2.3; extra == "docs"
Requires-Dist: sphinx-book-theme>=1.1.4; extra == "docs"
Requires-Dist: sphinx-autodoc-typehints; extra == "docs"
Requires-Dist: ipython>=8.8.0; extra == "docs"
Requires-Dist: myst-nb>=1.3.0; extra == "docs"
Requires-Dist: matplotlib>=3.10.0; extra == "docs"
Requires-Dist: sphinx-gallery>=0.19.0; extra == "docs"
Requires-Dist: sphinx-collections>=0.0.1; extra == "docs"
Requires-Dist: sphinx_contributors; extra == "docs"
Provides-Extra: prod
Requires-Dist: jax[tpu]!=0.7.2,>=0.6.0; extra == "prod"
Provides-Extra: dev
Dynamic: license-file
